src/uart_rx.v
module uart_rx #(
    parameter CLKS_PER_BAUD = 5208
)(
    input  wire       clk,
    input  wire       rst,
    input  wire       rx,
    output reg  [7:0] rx_data,
    output reg        rx_done
);

    localparam IDLE  = 2'b00;
    localparam START = 2'b01;
    localparam DATA  = 2'b10;
    localparam STOP  = 2'b11;

    localparam HALF = CLKS_PER_BAUD / 2;

    // 2-flop synchronizer
    reg rx_d1, rx_sync;
    always @(posedge clk) begin
        rx_d1   <= rx;
        rx_sync <= rx_d1;
    end

    reg [1:0]  state;
    reg [7:0]  shift_reg;
    reg [2:0]  bit_count;
    reg [12:0] cnt;        // counts clock cycles, resets at each new bit

    always @(posedge clk) begin
        if (rst) begin
            state     <= IDLE;
            rx_data   <= 0;
            rx_done   <= 0;
            bit_count <= 0;
            shift_reg <= 0;
            cnt       <= 0;
        end
        else begin
            rx_done <= 0;
            cnt     <= cnt + 1;   // always counting

            case (state)

                IDLE: begin
                    cnt <= 0;
                    if (!rx_sync) begin     // falling edge -- start bit begins
                        state <= START;
                    end
                end

                START: begin
                    // wait HALF a baud period to reach middle of start bit
                    if (cnt == HALF - 1) begin
                        cnt <= 0;
                        if (!rx_sync) begin // still low -- valid start bit
                            bit_count <= 0;
                            state     <= DATA;
                        end
                        else begin          // glitch -- go back
                            state <= IDLE;
                        end
                    end
                end

                DATA: begin
                    // wait one full baud period between samples
                    if (cnt == CLKS_PER_BAUD - 1) begin
                        cnt       <= 0;
                        shift_reg <= {rx_sync, shift_reg[7:1]};
                        if (bit_count == 7)
                            state <= STOP;
                        else
                            bit_count <= bit_count + 1;
                    end
                end

                STOP: begin
                    if (cnt == CLKS_PER_BAUD - 1) begin
                        cnt   <= 0;
                        state <= IDLE;
                        if (rx_sync) begin
                            rx_data <= shift_reg;
                            rx_done <= 1;
                        end
                    end
                end

            endcase
        end
    end

endmodule

src/uart_tx.v
module uart_tx (
    input  wire       clk,
    input  wire       rst,
    input  wire       baud_tick,
    input  wire [7:0] fifo_data,
    input  wire       fifo_empty,
    output reg        fifo_rd_en,
    output reg        tx
);

    localparam IDLE  = 2'b00;
    localparam START = 2'b01;
    localparam DATA  = 2'b10;
    localparam STOP  = 2'b11;

    reg [1:0] state;
    reg [7:0] shift_reg;
    reg [2:0] bit_count;

    always @(posedge clk) begin
        if (rst) begin
            state      <= IDLE;
            tx         <= 1;        // idle line sits HIGH
            fifo_rd_en <= 0;
            bit_count  <= 0;
            shift_reg  <= 0;
        end
        else begin
            fifo_rd_en <= 0;        // default low every cycle

            case (state)

                IDLE: begin
                    tx <= 1;
                    if (!fifo_empty) begin
                        shift_reg  <= fifo_data;  // latch byte from FIFO
                        fifo_rd_en <= 1;           // pulse rd_en to advance FIFO
                        state      <= START;
                    end
                end

                START: begin
                    if (baud_tick) begin
                        tx        <= 0;            // pull line LOW
                        bit_count <= 0;
                        state     <= DATA;
                    end
                end

                DATA: begin
                    if (baud_tick) begin
                        tx        <= shift_reg[0]; // send LSB
                        shift_reg <= shift_reg >> 1; // shift right, next bit moves to [0]
                        if (bit_count == 7)
                            state <= STOP;
                        else
                            bit_count <= bit_count + 1;
                    end
                end

                STOP: begin
                    if (baud_tick) begin
                        tx    <= 1;                // line back HIGH
                        state <= IDLE;
                    end
                end

            endcase
        end
    end

endmodule

src/fifo.v
module fifo #(
    parameter DEPTH = 8,
    parameter WIDTH = 8
)(
    input  wire             clk,
    input  wire             rst,
    input  wire             wr_en,
    input  wire             rd_en,
    input  wire [WIDTH-1:0] wr_data,
    output wire [WIDTH-1:0] rd_data,   
    output wire             full,
    output wire             empty
);

    reg [WIDTH-1:0] mem [0:DEPTH-1];
    reg [3:0] wr_ptr;
    reg [3:0] rd_ptr;

    assign empty   = (wr_ptr == rd_ptr);
    assign full    = (wr_ptr[2:0] == rd_ptr[2:0]) && (wr_ptr[3] != rd_ptr[3]);
    assign rd_data = mem[rd_ptr[2:0]];  /

    always @(posedge clk) begin
        if (rst) begin
            wr_ptr <= 0;
        end
        else if (wr_en && !full) begin
            mem[wr_ptr[2:0]] <= wr_data;
            wr_ptr <= wr_ptr + 1;
        end
    end

    always @(posedge clk) begin
        if (rst) begin
            rd_ptr <= 0;
        end
        else if (rd_en && !empty) begin
            rd_ptr <= rd_ptr + 1;
        end
    end

endmodule

src/baud_timer.v
module baud_timer #(
    parameter CLKS_PER_BAUD = 5208 //9600
)(
    input wire clk,
    input wire rst,
    output reg baud_tick
);


    reg [12:0] counter; 

    always @(posedge clk) begin
        if (rst) begin
            counter   <= 0;
            baud_tick <= 0;
        end
        else if (counter == CLKS_PER_BAUD - 1) begin // the next clock cycle will trigger baud_tick
            counter   <= 0;
            baud_tick <= 1;
        end
        else begin
            counter   <= counter + 1;
            baud_tick <= 0;
        end
    end

endmodule

src/uart_top.v
module uart_top #(
    parameter CLKS_PER_BAUD = 5208  // 50MHz / 9600 baud, override in tb
)(
    input  wire       clk,
    input  wire       rst,

    // FIFO write interface -- driven by user/testbench
    input  wire [7:0] wr_data,
    input  wire       wr_en,
    output wire       full,

    // serial pins
    output wire       tx,
    input  wire       rx_in,

    // RX output
    output wire [7:0] rx_data,
    output wire       rx_done
);

    // internal wires connecting modules together
    wire       baud_tick;
    wire [7:0] fifo_data;
    wire       fifo_empty;
    wire       fifo_rd_en;

    // baud timer -- drives everything
    baud_timer #(.CLKS_PER_BAUD(CLKS_PER_BAUD)) baud_inst (
        .clk      (clk),
        .rst      (rst),
        .baud_tick(baud_tick)
    );

    // FIFO -- buffers bytes waiting to transmit
    fifo fifo_inst (
        .clk    (clk),
        .rst    (rst),
        .wr_en  (wr_en),
        .rd_en  (fifo_rd_en),
        .wr_data(wr_data),
        .rd_data(fifo_data),
        .full   (full),
        .empty  (fifo_empty)
    );

    // TX -- drains FIFO and sends bytes serially
    uart_tx tx_inst (
        .clk       (clk),
        .rst       (rst),
        .baud_tick (baud_tick),
        .fifo_data (fifo_data),
        .fifo_empty(fifo_empty),
        .fifo_rd_en(fifo_rd_en),
        .tx        (tx)
    );

    // RX -- receives serial bytes
   uart_rx #(.CLKS_PER_BAUD(CLKS_PER_BAUD)) rx_inst (
    .clk    (clk),
    .rst    (rst),
    .rx     (rx_in),
    .rx_data(rx_data),
    .rx_done(rx_done)
);

endmodule

tb/uart_top_tb.v
`timescale 1ns/1ps

module uart_top_tb;

    reg        clk, rst;
    reg  [7:0] wr_data;
    reg        wr_en;
    wire       full, tx, rx_in;
    wire [7:0] rx_data;
    wire       rx_done;

    assign rx_in = tx;

    uart_top #(.CLKS_PER_BAUD(10)) dut (
        .clk(clk), .rst(rst),
        .wr_data(wr_data), .wr_en(wr_en), .full(full),
        .tx(tx), .rx_in(rx_in),
        .rx_data(rx_data), .rx_done(rx_done)
    );

    always #10 clk = ~clk;

    task send_and_check;
        input [7:0] byte_to_send;
        integer timeout;
        begin
            @(posedge clk); #1;
            wr_data = byte_to_send;
            wr_en   = 1;
            @(posedge clk); #1;
            wr_en = 0;

            timeout = 0;
            while (!rx_done && timeout < 50000) begin
                @(posedge clk);
                timeout = timeout + 1;
            end

            if (timeout >= 50000)
                $error("TIMEOUT -- rx_done never fired for 0x%h", byte_to_send);
            else if (rx_data == byte_to_send)
                $display("PASS -- sent 0x%h got 0x%h", byte_to_send, rx_data);
            else
                $error("FAIL -- sent 0x%h got 0x%h", byte_to_send, rx_data);
        end
    endtask

    initial begin
        $dumpfile("uart_top.vcd");
        $dumpvars(0, uart_top_tb);
        clk=0; rst=1; wr_en=0; wr_data=0;
        repeat(5) @(posedge clk);
        rst = 0;
        repeat(5) @(posedge clk);

        send_and_check(8'h55);
        send_and_check(8'h48);  // H
        send_and_check(8'h49);  // I
        send_and_check(8'h21);  // !
        send_and_check(8'hFF);
        send_and_check(8'h00);

        $display("back to back...");
        send_and_check(8'hAA);
        send_and_check(8'hBB);
        send_and_check(8'hCC);

        repeat(20) @(posedge clk);
        $display("ALL DONE");
        $finish;
    end

endmodule

uart_top.vcd
$date
	Sat Jun 06 18:32:14 2026
$end
$version
	Icarus Verilog
$end
$timescale
	1ps
$end
$scope module uart_top_tb $end
$var wire 1 ! rx_in $end
$var wire 1 " tx $end
$var wire 1 # rx_done $end
$var wire 8 $ rx_data [7:0] $end
$var wire 1 % full $end
$var reg 1 & clk $end
$var reg 1 ' rst $end
$var reg 8 ( wr_data [7:0] $end
$var reg 1 ) wr_en $end
$scope module dut $end
$var wire 1 & clk $end
$var wire 1 ' rst $end
$var wire 1 ! rx_in $end
$var wire 8 * wr_data [7:0] $end
$var wire 1 ) wr_en $end
$var wire 1 " tx $end
$var wire 1 # rx_done $end
$var wire 8 + rx_data [7:0] $end
$var wire 1 % full $end
$var wire 1 , fifo_rd_en $end
$var wire 1 - fifo_empty $end
$var wire 8 . fifo_data [7:0] $end
$var wire 1 / baud_tick $end
$scope module baud_inst $end
$var wire 1 & clk $end
$var wire 1 ' rst $end
$var reg 1 / baud_tick $end
$var reg 13 0 counter [12:0] $end
$upscope $end
$scope module fifo_inst $end
$var wire 1 & clk $end
$var wire 1 % full $end
$var wire 8 1 rd_data [7:0] $end
$var wire 1 ' rst $end
$var wire 8 2 wr_data [7:0] $end
$var wire 1 ) wr_en $end
$var wire 1 , rd_en $end
$var wire 1 - empty $end
$var reg 4 3 rd_ptr [3:0] $end
$var reg 4 4 wr_ptr [3:0] $end
$upscope $end
$scope module rx_inst $end
$var wire 1 & clk $end
$var wire 1 ' rst $end
$var wire 1 ! rx $end
$var reg 3 5 bit_count [2:0] $end
$var reg 13 6 cnt [12:0] $end
$var reg 1 7 rx_d1 $end
$var reg 8 8 rx_data [7:0] $end
$var reg 1 # rx_done $end
$var reg 1 9 rx_sync $end
$var reg 8 : shift_reg [7:0] $end
$var reg 2 ; state [1:0] $end
$upscope $end
$scope module tx_inst $end
$var wire 1 / baud_tick $end
$var wire 1 & clk $end
$var wire 8 < fifo_data [7:0] $end
$var wire 1 - fifo_empty $end
$var wire 1 ' rst $end
$var reg 3 = bit_count [2:0] $end
$var reg 1 , fifo_rd_en $end
$var reg 8 > shift_reg [7:0] $end
$var reg 2 ? state [1:0] $end
$var reg 1 " tx $end
$upscope $end
$upscope $end
$scope task send_and_check $end
$var reg 8 @ byte_to_send [7:0] $end
$var integer 32 A timeout [31:0] $end
$upscope $end
$upscope $end
$enddefinitions $end
#0
$dumpvars
bx A
bx @
bx ?
bx >
bx =
bx <
bx ;
bx :
x9
bx 8
x7
bx 6
bx 5
bx 4
bx 3
b0 2
bx 1
bx 0
x/
bx .
x-
x,
bx +
b0 *
0)
b0 (
1'
0&
x%
bx $
x#
x"
x!
$end
#10000
0%
0/
b0 0
1-
b0 4
b0 3
b0 >
b0 =
0,
1!
1"
b0 ?
b0 6
b0 :
b0 5
0#
b0 $
b0 +
b0 8
b0 ;
1&
#20000
0&
#30000
17
1&
#40000
0&
#50000
19
1&
#60000
0&
#70000
1&
#80000
0&
#90000
b1 0
b0 6
0'
1&
#100000
0&
#110000
b0 6
b10 0
1&
#120000
0&
#130000
b11 0
b0 6
1&
#140000
0&
#150000
b0 6
b100 0
1&
#160000
0&
#170000
b101 0
b0 6
1&
#180000
0&
#190000
b0 6
b110 0
b1010101 @
1&
#200000
0&
#210000
b111 0
b0 6
1&
#211000
1)
b1010101 (
b1010101 *
b1010101 2
#220000
0&
#230000
b0 6
0-
b1 4
b1010101 .
b1010101 1
b1010101 <
b1000 0
1&
#231000
b0 A
0)
#240000
0&
#250000
b1001 0
b1 ?
1,
b1010101 >
b0 6
b1 A
1&
#260000
0&
#270000
bx .
bx 1
bx <
b0 6
0,
1-
b1 3
1/
b0 0
b10 A
1&
#280000
0&
#290000
0/
b1 0
b10 ?
0!
0"
b0 6
b11 A
1&
#300000
0&
#310000
b0 6
07
b10 0
b100 A
1&
#320000
0&
#330000
b11 0
09
b0 6
b101 A
1&
#340000
0&
#350000
b1 ;
b0 6
b100 0
b110 A
1&
#360000
0&
#370000
b101 0
b1 6
b111 A
1&
#380000
0&
#390000
b10 6
b110 0
b1000 A
1&
#400000
0&
#410000
b111 0
b11 6
b1001 A
1&
#420000
0&
#430000
b100 6
b1000 0
b1010 A
1&
#440000
0&
#450000
b1001 0
b10 ;
b0 6
b1011 A
1&
#460000
0&
#470000
b1 6
1/
b0 0
b1100 A
1&
#480000
0&
#490000
0/
b1 0
b1 =
b101010 >
1!
1"
b10 6
b1101 A
1&
#500000
0&
#510000
b11 6
17
b10 0
b1110 A
1&
#520000
0&
#530000
b11 0
19
b100 6
b1111 A
1&
#540000
0&
#550000
b101 6
b100 0
b10000 A
1&
#560000
0&
#570000
b101 0
b110 6
b10001 A
1&
#580000
0&
#590000
b111 6
b110 0
b10010 A
1&
#600000
0&
#610000
b111 0
b1000 6
b10011 A
1&
#620000
0&
#630000
b1001 6
b1000 0
b10100 A
1&
#640000
0&
#650000
b1001 0
b1 5
b10000000 :
b0 6
b10101 A
1&
#660000
0&
#670000
b1 6
1/
b0 0
b10110 A
1&
#680000
0&
#690000
0/
b1 0
b10 =
b10101 >
0!
0"
b10 6
b10111 A
1&
#700000
0&
#710000
b11 6
07
b10 0
b11000 A
1&
#720000
0&
#730000
b11 0
09
b100 6
b11001 A
1&
#740000
0&
#750000
b101 6
b100 0
b11010 A
1&
#760000
0&
#770000
b101 0
b110 6
b11011 A
1&
#780000
0&
#790000
b111 6
b110 0
b11100 A
1&
#800000
0&
#810000
b111 0
b1000 6
b11101 A
1&
#820000
0&
#830000
b1001 6
b1000 0
b11110 A
1&
#840000
0&
#850000
b1001 0
b10 5
b1000000 :
b0 6
b11111 A
1&
#860000
0&
#870000
b1 6
1/
b0 0
b100000 A
1&
#880000
0&
#890000
0/
b1 0
b11 =
b1010 >
1!
1"
b10 6
b100001 A
1&
#900000
0&
#910000
b11 6
17
b10 0
b100010 A
1&
#920000
0&
#930000
b11 0
19
b100 6
b100011 A
1&
#940000
0&
#950000
b101 6
b100 0
b100100 A
1&
#960000
0&
#970000
b101 0
b110 6
b100101 A
1&
#980000
0&
#990000
b111 6
b110 0
b100110 A
1&
#1000000
0&
#1010000
b111 0
b1000 6
b100111 A
1&
#1020000
0&
#1030000
b1001 6
b1000 0
b101000 A
1&
#1040000
0&
#1050000
b1001 0
b11 5
b10100000 :
b0 6
b101001 A
1&
#1060000
0&
#1070000
b1 6
1/
b0 0
b101010 A
1&
#1080000
0&
#1090000
0/
b1 0
b100 =
b101 >
0!
0"
b10 6
b101011 A
1&
#1100000
0&
#1110000
b11 6
07
b10 0
b101100 A
1&
#1120000
0&
#1130000
b11 0
09
b100 6
b101101 A
1&
#1140000
0&
#1150000
b101 6
b100 0
b101110 A
1&
#1160000
0&
#1170000
b101 0
b110 6
b101111 A
1&
#1180000
0&
#1190000
b111 6
b110 0
b110000 A
1&
#1200000
0&
#1210000
b111 0
b1000 6
b110001 A
1&
#1220000
0&
#1230000
b1001 6
b1000 0
b110010 A
1&
#1240000
0&
#1250000
b1001 0
b100 5
b1010000 :
b0 6
b110011 A
1&
#1260000
0&
#1270000
b1 6
1/
b0 0
b110100 A
1&
#1280000
0&
#1290000
0/
b1 0
b101 =
b10 >
1!
1"
b10 6
b110101 A
1&
#1300000
0&
#1310000
b11 6
17
b10 0
b110110 A
1&
#1320000
0&
#1330000
b11 0
19
b100 6
b110111 A
1&
#1340000
0&
#1350000
b101 6
b100 0
b111000 A
1&
#1360000
0&
#1370000
b101 0
b110 6
b111001 A
1&
#1380000
0&
#1390000
b111 6
b110 0
b111010 A
1&
#1400000
0&
#1410000
b111 0
b1000 6
b111011 A
1&
#1420000
0&
#1430000
b1001 6
b1000 0
b111100 A
1&
#1440000
0&
#1450000
b1001 0
b101 5
b10101000 :
b0 6
b111101 A
1&
#1460000
0&
#1470000
b1 6
1/
b0 0
b111110 A
1&
#1480000
0&
#1490000
0/
b1 0
b110 =
b1 >
0!
0"
b10 6
b111111 A
1&
#1500000
0&
#1510000
b11 6
07
b10 0
b1000000 A
1&
#1520000
0&
#1530000
b11 0
09
b100 6
b1000001 A
1&
#1540000
0&
#1550000
b101 6
b100 0
b1000010 A
1&
#1560000
0&
#1570000
b101 0
b110 6
b1000011 A
1&
#1580000
0&
#1590000
b111 6
b110 0
b1000100 A
1&
#1600000
0&
#1610000
b111 0
b1000 6
b1000101 A
1&
#1620000
0&
#1630000
b1001 6
b1000 0
b1000110 A
1&
#1640000
0&
#1650000
b1001 0
b110 5
b1010100 :
b0 6
b1000111 A
1&
#1660000
0&
#1670000
b1 6
1/
b0 0
b1001000 A
1&
#1680000
0&
#1690000
0/
b1 0
b111 =
b0 >
1!
1"
b10 6
b1001001 A
1&
#1700000
0&
#1710000
b11 6
17
b10 0
b1001010 A
1&
#1720000
0&
#1730000
b11 0
19
b100 6
b1001011 A
1&
#1740000
0&
#1750000
b101 6
b100 0
b1001100 A
1&
#1760000
0&
#1770000
b101 0
b110 6
b1001101 A
1&
#1780000
0&
#1790000
b111 6
b110 0
b1001110 A
1&
#1800000
0&
#1810000
b111 0
b1000 6
b1001111 A
1&
#1820000
0&
#1830000
b1001 6
b1000 0
b1010000 A
1&
#1840000
0&
#1850000
b1001 0
b111 5
b10101010 :
b0 6
b1010001 A
1&
#1860000
0&
#1870000
b1 6
1/
b0 0
b1010010 A
1&
#1880000
0&
#1890000
0/
b1 0
b11 ?
0!
0"
b10 6
b1010011 A
1&
#1900000
0&
#1910000
b11 6
07
b10 0
b1010100 A
1&
#1920000
0&
#1930000
b11 0
09
b100 6
b1010101 A
1&
#1940000
0&
#1950000
b101 6
b100 0
b1010110 A
1&
#1960000
0&
#1970000
b101 0
b110 6
b1010111 A
1&
#1980000
0&
#1990000
b111 6
b110 0
b1011000 A
1&
#2000000
0&
#2010000
b111 0
b1000 6
b1011001 A
1&
#2020000
0&
#2030000
b1001 6
b1000 0
b1011010 A
1&
#2040000
0&
#2050000
b1001 0
b11 ;
b1010101 :
b0 6
b1011011 A
1&
#2060000
0&
#2070000
b1 6
1/
b0 0
b1011100 A
1&
#2080000
0&
#2090000
0/
b1 0
b0 ?
1!
1"
b10 6
b1011101 A
1&
#2100000
0&
#2110000
b11 6
17
b10 0
b1011110 A
1&
#2120000
0&
#2130000
b11 0
19
b100 6
b1011111 A
1&
#2140000
0&
#2150000
b101 6
b100 0
b1100000 A
1&
#2160000
0&
#2170000
b101 0
b110 6
b1100001 A
1&
#2180000
0&
#2190000
b111 6
b110 0
b1100010 A
1&
#2200000
0&
#2210000
b111 0
b1000 6
b1100011 A
1&
#2220000
0&
#2230000
b1001 6
b1000 0
b1100100 A
1&
#2240000
0&
#2250000
b1001 0
1#
b1010101 $
b1010101 +
b1010101 8
b0 ;
b0 6
b1100101 A
1&
#2260000
0&
#2270000
b0 6
0#
1/
b0 0
b1001000 @
b1100110 A
1&
#2280000
0&
#2290000
0/
b1 0
b0 6
1&
#2291000
1)
b1001000 (
b1001000 *
b1001000 2
#2300000
0&
#2310000
b0 6
0-
b10 4
b1001000 .
b1001000 1
b1001000 <
b10 0
1&
#2311000
b0 A
0)
#2320000
0&
#2330000
b11 0
b1 ?
1,
b1001000 >
b0 6
b1 A
1&
#2340000
0&
#2350000
bx .
bx 1
bx <
b0 6
0,
1-
b10 3
b100 0
b10 A
1&
#2360000
0&
#2370000
b101 0
b0 6
b11 A
1&
#2380000
0&
#2390000
b0 6
b110 0
b100 A
1&
#2400000
0&
#2410000
b111 0
b0 6
b101 A
1&
#2420000
0&
#2430000
b0 6
b1000 0
b110 A
1&
#2440000
0&
#2450000
b1001 0
b0 6
b111 A
1&
#2460000
0&
#2470000
b0 6
1/
b0 0
b1000 A
1&
#2480000
0&
#2490000
0/
b1 0
b10 ?
b0 =
0!
0"
b0 6
b1001 A
1&
#2500000
0&
#2510000
b0 6
07
b10 0
b1010 A
1&
#2520000
0&
#2530000
b11 0
09
b0 6
b1011 A
1&
#2540000
0&
#2550000
b1 ;
b0 6
b100 0
b1100 A
1&
#2560000
0&
#2570000
b101 0
b1 6
b1101 A
1&
#2580000
0&
#2590000
b10 6
b110 0
b1110 A
1&
#2600000
0&
#2610000
b111 0
b11 6
b1111 A
1&
#2620000
0&
#2630000
b100 6
b1000 0
b10000 A
1&
#2640000
0&
#2650000
b1001 0
b10 ;
b0 5
b0 6
b10001 A
1&
#2660000
0&
#2670000
b1 6
1/
b0 0
b10010 A
1&
#2680000
0&
#2690000
0/
b1 0
b1 =
b100100 >
b10 6
b10011 A
1&
#2700000
0&
#2710000
b11 6
b10 0
b10100 A
1&
#2720000
0&
#2730000
b11 0
b100 6
b10101 A
1&
#2740000
0&
#2750000
b101 6
b100 0
b10110 A
1&
#2760000
0&
#2770000
b101 0
b110 6
b10111 A
1&
#2780000
0&
#2790000
b111 6
b110 0
b11000 A
1&
#2800000
0&
#2810000
b111 0
b1000 6
b11001 A
1&
#2820000
0&
#2830000
b1001 6
b1000 0
b11010 A
1&
#2840000
0&
#2850000
b1001 0
b1 5
b101010 :
b0 6
b11011 A
1&
#2860000
0&
#2870000
b1 6
1/
b0 0
b11100 A
1&
#2880000
0&
#2890000
0/
b1 0
b10 =
b10010 >
b10 6
b11101 A
1&
#2900000
0&
#2910000
b11 6
b10 0
b11110 A
1&
#2920000
0&
#2930000
b11 0
b100 6
b11111 A
1&
#2940000
0&
#2950000
b101 6
b100 0
b100000 A
1&
#2960000
0&
#2970000
b101 0
b110 6
b100001 A
1&
#2980000
0&
#2990000
b111 6
b110 0
b100010 A
1&
#3000000
0&
#3010000
b111 0
b1000 6
b100011 A
1&
#3020000
0&
#3030000
b1001 6
b1000 0
b100100 A
1&
#3040000
0&
#3050000
b1001 0
b10 5
b10101 :
b0 6
b100101 A
1&
#3060000
0&
#3070000
b1 6
1/
b0 0
b100110 A
1&
#3080000
0&
#3090000
0/
b1 0
b11 =
b1001 >
b10 6
b100111 A
1&
#3100000
0&
#3110000
b11 6
b10 0
b101000 A
1&
#3120000
0&
#3130000
b11 0
b100 6
b101001 A
1&
#3140000
0&
#3150000
b101 6
b100 0
b101010 A
1&
#3160000
0&
#3170000
b101 0
b110 6
b101011 A
1&
#3180000
0&
#3190000
b111 6
b110 0
b101100 A
1&
#3200000
0&
#3210000
b111 0
b1000 6
b101101 A
1&
#3220000
0&
#3230000
b1001 6
b1000 0
b101110 A
1&
#3240000
0&
#3250000
b1001 0
b11 5
b1010 :
b0 6
b101111 A
1&
#3260000
0&
#3270000
b1 6
1/
b0 0
b110000 A
1&
#3280000
0&
#3290000
0/
b1 0
b100 =
b100 >
1!
1"
b10 6
b110001 A
1&
#3300000
0&
#3310000
b11 6
17
b10 0
b110010 A
1&
#3320000
0&
#3330000
b11 0
19
b100 6
b110011 A
1&
#3340000
0&
#3350000
b101 6
b100 0
b110100 A
1&
#3360000
0&
#3370000
b101 0
b110 6
b110101 A
1&
#3380000
0&
#3390000
b111 6
b110 0
b110110 A
1&
#3400000
0&
#3410000
b111 0
b1000 6
b110111 A
1&
#3420000
0&
#3430000
b1001 6
b1000 0
b111000 A
1&
#3440000
0&
#3450000
b1001 0
b100 5
b10000101 :
b0 6
b111001 A
1&
#3460000
0&
#3470000
b1 6
1/
b0 0
b111010 A
1&
#3480000
0&
#3490000
0/
b1 0
b101 =
b10 >
0!
0"
b10 6
b111011 A
1&
#3500000
0&
#3510000
b11 6
07
b10 0
b111100 A
1&
#3520000
0&
#3530000
b11 0
09
b100 6
b111101 A
1&
#3540000
0&
#3550000
b101 6
b100 0
b111110 A
1&
#3560000
0&
#3570000
b101 0
b110 6
b111111 A
1&
#3580000
0&
#3590000
b111 6
b110 0
b1000000 A
1&
#3600000
0&
#3610000
b111 0
b1000 6
b1000001 A
1&
#3620000
0&
#3630000
b1001 6
b1000 0
b1000010 A
1&
#3640000
0&
#3650000
b1001 0
b101 5
b1000010 :
b0 6
b1000011 A
1&
#3660000
0&
#3670000
b1 6
1/
b0 0
b1000100 A
1&
#3680000
0&
#3690000
0/
b1 0
b110 =
b1 >
b10 6
b1000101 A
1&
#3700000
0&
#3710000
b11 6
b10 0
b1000110 A
1&
#3720000
0&
#3730000
b11 0
b100 6
b1000111 A
1&
#3740000
0&
#3750000
b101 6
b100 0
b1001000 A
1&
#3760000
0&
#3770000
b101 0
b110 6
b1001001 A
1&
#3780000
0&
#3790000
b111 6
b110 0
b1001010 A
1&
#3800000
0&
#3810000
b111 0
b1000 6
b1001011 A
1&
#3820000
0&
#3830000
b1001 6
b1000 0
b1001100 A
1&
#3840000
0&
#3850000
b1001 0
b110 5
b100001 :
b0 6
b1001101 A
1&
#3860000
0&
#3870000
b1 6
1/
b0 0
b1001110 A
1&
#3880000
0&
#3890000
0/
b1 0
b111 =
b0 >
1!
1"
b10 6
b1001111 A
1&
#3900000
0&
#3910000
b11 6
17
b10 0
b1010000 A
1&
#3920000
0&
#3930000
b11 0
19
b100 6
b1010001 A
1&
#3940000
0&
#3950000
b101 6
b100 0
b1010010 A
1&
#3960000
0&
#3970000
b101 0
b110 6
b1010011 A
1&
#3980000
0&
#3990000
b111 6
b110 0
b1010100 A
1&
#4000000
0&
#4010000
b111 0
b1000 6
b1010101 A
1&
#4020000
0&
#4030000
b1001 6
b1000 0
b1010110 A
1&
#4040000
0&
#4050000
b1001 0
b111 5
b10010000 :
b0 6
b1010111 A
1&
#4060000
0&
#4070000
b1 6
1/
b0 0
b1011000 A
1&
#4080000
0&
#4090000
0/
b1 0
b11 ?
0!
0"
b10 6
b1011001 A
1&
#4100000
0&
#4110000
b11 6
07
b10 0
b1011010 A
1&
#4120000
0&
#4130000
b11 0
09
b100 6
b1011011 A
1&
#4140000
0&
#4150000
b101 6
b100 0
b1011100 A
1&
#4160000
0&
#4170000
b101 0
b110 6
b1011101 A
1&
#4180000
0&
#4190000
b111 6
b110 0
b1011110 A
1&
#4200000
0&
#4210000
b111 0
b1000 6
b1011111 A
1&
#4220000
0&
#4230000
b1001 6
b1000 0
b1100000 A
1&
#4240000
0&
#4250000
b1001 0
b11 ;
b1001000 :
b0 6
b1100001 A
1&
#4260000
0&
#4270000
b1 6
1/
b0 0
b1100010 A
1&
#4280000
0&
#4290000
0/
b1 0
b0 ?
1!
1"
b10 6
b1100011 A
1&
#4300000
0&
#4310000
b11 6
17
b10 0
b1100100 A
1&
#4320000
0&
#4330000
b11 0
19
b100 6
b1100101 A
1&
#4340000
0&
#4350000
b101 6
b100 0
b1100110 A
1&
#4360000
0&
#4370000
b101 0
b110 6
b1100111 A
1&
#4380000
0&
#4390000
b111 6
b110 0
b1101000 A
1&
#4400000
0&
#4410000
b111 0
b1000 6
b1101001 A
1&
#4420000
0&
#4430000
b1001 6
b1000 0
b1101010 A
1&
#4440000
0&
#4450000
b1001 0
1#
b1001000 $
b1001000 +
b1001000 8
b0 ;
b0 6
b1101011 A
1&
#4460000
0&
#4470000
b0 6
0#
1/
b0 0
b1001001 @
b1101100 A
1&
#4480000
0&
#4490000
0/
b1 0
b0 6
1&
#4491000
1)
b1001001 (
b1001001 *
b1001001 2
#4500000
0&
#4510000
b0 6
0-
b11 4
b1001001 .
b1001001 1
b1001001 <
b10 0
1&
#4511000
b0 A
0)
#4520000
0&
#4530000
b11 0
b1 ?
1,
b1001001 >
b0 6
b1 A
1&
#4540000
0&
#4550000
bx .
bx 1
bx <
b0 6
0,
1-
b11 3
b100 0
b10 A
1&
#4560000
0&
#4570000
b101 0
b0 6
b11 A
1&
#4580000
0&
#4590000
b0 6
b110 0
b100 A
1&
#4600000
0&
#4610000
b111 0
b0 6
b101 A
1&
#4620000
0&
#4630000
b0 6
b1000 0
b110 A
1&
#4640000
0&
#4650000
b1001 0
b0 6
b111 A
1&
#4660000
0&
#4670000
b0 6
1/
b0 0
b1000 A
1&
#4680000
0&
#4690000
0/
b1 0
b10 ?
b0 =
0!
0"
b0 6
b1001 A
1&
#4700000
0&
#4710000
b0 6
07
b10 0
b1010 A
1&
#4720000
0&
#4730000
b11 0
09
b0 6
b1011 A
1&
#4740000
0&
#4750000
b1 ;
b0 6
b100 0
b1100 A
1&
#4760000
0&
#4770000
b101 0
b1 6
b1101 A
1&
#4780000
0&
#4790000
b10 6
b110 0
b1110 A
1&
#4800000
0&
#4810000
b111 0
b11 6
b1111 A
1&
#4820000
0&
#4830000
b100 6
b1000 0
b10000 A
1&
#4840000
0&
#4850000
b1001 0
b10 ;
b0 5
b0 6
b10001 A
1&
#4860000
0&
#4870000
b1 6
1/
b0 0
b10010 A
1&
#4880000
0&
#4890000
0/
b1 0
b1 =
b100100 >
1!
1"
b10 6
b10011 A
1&
#4900000
0&
#4910000
b11 6
17
b10 0
b10100 A
1&
#4920000
0&
#4930000
b11 0
19
b100 6
b10101 A
1&
#4940000
0&
#4950000
b101 6
b100 0
b10110 A
1&
#4960000
0&
#4970000
b101 0
b110 6
b10111 A
1&
#4980000
0&
#4990000
b111 6
b110 0
b11000 A
1&
#5000000
0&
#5010000
b111 0
b1000 6
b11001 A
1&
#5020000
0&
#5030000
b1001 6
b1000 0
b11010 A
1&
#5040000
0&
#5050000
b1001 0
b1 5
b10100100 :
b0 6
b11011 A
1&
#5060000
0&
#5070000
b1 6
1/
b0 0
b11100 A
1&
#5080000
0&
#5090000
0/
b1 0
b10 =
b10010 >
0!
0"
b10 6
b11101 A
1&
#5100000
0&
#5110000
b11 6
07
b10 0
b11110 A
1&
#5120000
0&
#5130000
b11 0
09
b100 6
b11111 A
1&
#5140000
0&
#5150000
b101 6
b100 0
b100000 A
1&
#5160000
0&
#5170000
b101 0
b110 6
b100001 A
1&
#5180000
0&
#5190000
b111 6
b110 0
b100010 A
1&
#5200000
0&
#5210000
b111 0
b1000 6
b100011 A
1&
#5220000
0&
#5230000
b1001 6
b1000 0
b100100 A
1&
#5240000
0&
